cmdix/__init__.py
cmdix/__main__.py
cmdix/compressor.py
cmdix/exception.py
cmdix/hasher.py
cmdix/lib.py
cmdix/command/__init__.py
cmdix/command/arch.py
cmdix/command/base64.py
cmdix/command/basename.py
cmdix/command/bunzip2.py
cmdix/command/bzip2.py
cmdix/command/cal.py
cmdix/command/cat.py
cmdix/command/chmod.py
cmdix/command/chown.py
cmdix/command/chroot.py
cmdix/command/clear.py
cmdix/command/cp.py
cmdix/command/crond.py
cmdix/command/diff.py
cmdix/command/dirname.py
cmdix/command/env.py
cmdix/command/expand.py
cmdix/command/gunzip.py
cmdix/command/gzip.py
cmdix/command/httpd.py
cmdix/command/id.py
cmdix/command/init.py
cmdix/command/kill.py
cmdix/command/ln.py
cmdix/command/logger.py
cmdix/command/ls.py
cmdix/command/md5sum.py
cmdix/command/mkdir.py
cmdix/command/mktemp.py
cmdix/command/more.py
cmdix/command/mount.py
cmdix/command/mv.py
cmdix/command/nl.py
cmdix/command/pwd.py
cmdix/command/rm.py
cmdix/command/rmdir.py
cmdix/command/sendmail.py
cmdix/command/seq.py
cmdix/command/sh.py
cmdix/command/sha1sum.py
cmdix/command/sha224sum.py
cmdix/command/sha256sum.py
cmdix/command/sha384sum.py
cmdix/command/sha512sum.py
cmdix/command/shred.py
cmdix/command/shuf.py
cmdix/command/sleep.py
cmdix/command/sort.py
cmdix/command/tail.py
cmdix/command/tar.py
cmdix/command/tee.py
cmdix/command/touch.py
cmdix/command/uname.py
cmdix/command/uptime.py
cmdix/command/uuidgen.py
cmdix/command/watch.py
cmdix/command/wc.py
cmdix/command/wget.py
cmdix/command/whoami.py
cmdix/command/yes.py
cmdix/command/zip.py
cmdix/compat/__init__.py
cmdix/compat/py311.py
cmdix/compat/py39.py
cmdix-3.2.0.dist-info/LICENSE
cmdix-3.2.0.dist-info/METADATA
cmdix-3.2.0.dist-info/WHEEL
cmdix-3.2.0.dist-info/entry_points.txt
cmdix-3.2.0.dist-info/top_level.txt
cmdix-3.2.0.dist-info/RECORD
