Metadata-Version: 2.2
Name: cmdix
Version: 3.2.0
Summary: Unix commands in Pure Python
Author-email: "Jason R. Coombs" <jaraco@jaraco.com>
Project-URL: Source, https://github.com/jaraco/cmdix
Classifier: Development Status :: 5 - Production/Stable
Classifier: Intended Audience :: Developers
Classifier: License :: OSI Approved :: MIT License
Classifier: Programming Language :: Python :: 3
Classifier: Programming Language :: Python :: 3 :: Only
Classifier: Environment :: Console
Classifier: Topic :: System :: Shells
Classifier: Topic :: Utilities
Requires-Python: >=3.9
License-File: LICENSE
Requires-Dist: importlib_resources
Requires-Dist: backports.hook_compressed; python_version < "3.10"
Requires-Dist: more_itertools
Requires-Dist: python-dateutil
Provides-Extra: test
Requires-Dist: pytest!=8.1.*,>=6; extra == "test"
Provides-Extra: doc
Requires-Dist: sphinx>=3.5; extra == "doc"
Requires-Dist: jaraco.packaging>=9.3; extra == "doc"
Requires-Dist: rst.linker>=1.9; extra == "doc"
Requires-Dist: furo; extra == "doc"
Requires-Dist: sphinx-lint; extra == "doc"
Provides-Extra: check
Requires-Dist: pytest-checkdocs>=2.4; extra == "check"
Requires-Dist: pytest-ruff>=0.2.1; sys_platform != "cygwin" and extra == "check"
Provides-Extra: cover
Requires-Dist: pytest-cov; extra == "cover"
Provides-Extra: enabler
Requires-Dist: pytest-enabler>=2.2; extra == "enabler"
Provides-Extra: type
Requires-Dist: pytest-mypy; extra == "type"
Requires-Dist: types-backports; extra == "type"
